dpt_settings/__init__.py
dpt_settings-1.1.4.data/data/docs/LICENSE
dpt_settings-1.1.4.data/data/docs/README
dpt_settings-1.1.4.dist-info/LICENSE
dpt_settings-1.1.4.dist-info/METADATA
dpt_settings-1.1.4.dist-info/WHEEL
dpt_settings-1.1.4.dist-info/top_level.txt
dpt_settings-1.1.4.dist-info/RECORD
