Metadata-Version: 2.1
Name: dpt-settings
Version: 1.1.4
Summary: JSON-based settings environment made easy
Home-page: https://www.direct-netware.de/redirect?dpt;settings
Author: direct Netware Group et al.
Author-email: web@direct-netware.de
License: MPL2
Platform: any
Classifier: Intended Audience :: Developers
Classifier: License :: OSI Approved :: Mozilla Public License 2.0 (MPL 2.0)
Classifier: Operating System :: OS Independent
Classifier: Programming Language :: Python
Classifier: Topic :: Software Development :: Libraries :: Python Modules
Requires-Dist: dpt-runtime (<3,>=2.1.0)
